[
  {
    "judul": "Sebanyak 33.565 Unit Kendaraan Melintasi Tol Pekanbaru-Bangkinang",
    "kategori": "Resumatra",
    "waktu_publish": "1 menit yang lalu\n14 April 2024, 10:50",
    "waktu_scraping": "10:51:53\nSunday, 14 April 2024",
    "hash_code": "e54f2db6913061d24cbc89f215d6f33d89dd1e10",
    "waktu_real_publish": "2024-04-14T10:50:00"
  },
  {
    "judul": "Gol Tchouameni Bawa Real Madrid Menang Tipis 1-0 Atas Mallorca",
    "kategori": "Sport",
    "waktu_publish": "10 menit yang lalu\n14 April 2024, 10:41",
    "waktu_scraping": "10:41:53\nSunday, 14 April 2024",
    "hash_code": "cd640f3883180fe6e67b4007f4975bb8cb5da321",
    "waktu_real_publish": "2024-04-14T10:41:00"
  },
  {
    "judul": "Siap-Siap, WhatsApp Segera Pakai Chatbot AI, Apa yang Menarik?",
    "kategori": "Network",
    "waktu_publish": "14 menit yang lalu\n14 April 2024, 10:37",
    "waktu_scraping": "10:46:53\nSunday, 14 April 2024",
    "hash_code": "c5dad2b953c51057cb77c70941ebb33ea4f23cb7",
    "waktu_real_publish": "2024-04-14T10:37:00"
  },
  {
    "judul": "Cek Biaya Kuliah UNY Program Sarjana Terapan (D4), Ada 10 Tingkat UKT",
    "kategori": "Network",
    "waktu_publish": "15 menit yang lalu\n14 April 2024, 10:36",
    "waktu_scraping": "10:46:53\nSunday, 14 April 2024",
    "hash_code": "e91e3c44f9adea7b0ca47fd8259a6dcec1a5dc38",
    "waktu_real_publish": "2024-04-14T10:36:00"
  },
  {
    "judul": "Kiat Mobil Aman dan Nyaman Selama Arus Balik",
    "kategori": "Ramadhan",
    "waktu_publish": "21 menit yang lalu\n14 April 2024, 10:30",
    "waktu_scraping": "10:36:53\nSunday, 14 April 2024",
    "hash_code": "c3619649043bf280b97e329b5713c7246532d5e1",
    "waktu_real_publish": "2024-04-14T10:30:00"
  },
  {
    "judul": "Puncak Arus Balik, Ini Jalur Alternatif di Jabar yang Bisa Dapat Dimanfaatkan Pemudik",
    "kategori": "Rejabar",
    "waktu_publish": "25 menit yang lalu\n14 April 2024, 10:26",
    "waktu_scraping": "10:26:53\nSunday, 14 April 2024",
    "hash_code": "74b3ae42b5c6587fcb7b77bdd72b0be5f7e3e113",
    "waktu_real_publish": "2024-04-14T10:26:00"
  },
  {
    "judul": "Seruan Sholat di Masjid Al Aqsa Disambut Serius, Hadang Ritual Sapi Merah di Idul Fitri?",
    "kategori": "Khazanah",
    "waktu_publish": "28 menit yang lalu\n14 April 2024, 10:23",
    "waktu_scraping": "10:26:53\nSunday, 14 April 2024",
    "hash_code": "673eaa7ee76b25d314d3d4bd17788c1dda40e400",
    "waktu_real_publish": "2024-04-14T10:23:00"
  },
  {
    "judul": "Seruan Sholat di Masjid Al Aqsa Disambut Serius, Adang Ritual Sapi Merah pada Idul Fitri?",
    "kategori": "Khazanah",
    "waktu_publish": "28 menit yang lalu\n14 April 2024, 10:23",
    "waktu_scraping": "10:36:53\nSunday, 14 April 2024",
    "hash_code": "c421607810831868cc4b3b6d20292fb2ac0bbc25",
    "waktu_real_publish": "2024-04-14T10:23:00"
  },
  {
    "judul": "Foto Serangan Rudal Iran ke Wilayah Israel",
    "kategori": "Visual",
    "waktu_publish": "35 menit yang lalu\n14 April 2024, 10:16",
    "waktu_scraping": "10:16:53\nSunday, 14 April 2024",
    "hash_code": "6df079cb4c1c2f47faabbc7f6d6fc8058d17458c",
    "waktu_real_publish": "2024-04-14T10:16:00"
  },
  {
    "judul": "Siap Layani Arus Balik, Posko Mudik BRImo Hadir di Rute Strategis",
    "kategori": "Ekonomi",
    "waktu_publish": "41 menit yang lalu\n14 April 2024, 10:10",
    "waktu_scraping": "10:11:53\nSunday, 14 April 2024",
    "hash_code": "95dfe6eeb32138da8e174d00a0467cdbf2e4e51d",
    "waktu_real_publish": "2024-04-14T10:10:00"
  },
  {
    "judul": "Tips dari Psikolog Persiapkan Fisik Anak Jelang Masuk Sekolah",
    "kategori": "Ameera",
    "waktu_publish": "41 menit yang lalu\n14 April 2024, 10:10",
    "waktu_scraping": "10:11:53\nSunday, 14 April 2024",
    "hash_code": "7b6c932dab3b13057e882482a6ec0e330379b404",
    "waktu_real_publish": "2024-04-14T10:10:00"
  },
  {
    "judul": "Ahad Pagi, Cuaca Sebagian Besar Wilayah di Indonesia Cerah Berawan",
    "kategori": "News",
    "waktu_publish": "1 jam yang lalu\n14 April 2024, 09:50",
    "waktu_scraping": "09:51:53\nSunday, 14 April 2024",
    "hash_code": "37b1160c4422d2e5e240a74deb6e8ae1e85f6848",
    "waktu_real_publish": "2024-04-14T09:50:00"
  },
  {
    "judul": "Padahal Cuma 6 Hari, Mengapa Puasa Syawal Pahala Besar Sampai Dihitung Satu Tahun?",
    "kategori": "Ramadhan",
    "waktu_publish": "1 jam yang lalu\n14 April 2024, 09:47",
    "waktu_scraping": "09:51:53\nSunday, 14 April 2024",
    "hash_code": "20a8894fd3cf1bf68a3f9d5ec554c2272e8b20a6",
    "waktu_real_publish": "2024-04-14T09:47:00"
  },
  {
    "judul": "Persiapan Arus Balik Lebaran, Apa Saja yang Wajib Diperhatikan ?",
    "kategori": "Network",
    "waktu_publish": "1 jam yang lalu\n14 April 2024, 09:46",
    "waktu_scraping": "09:51:53\nSunday, 14 April 2024",
    "hash_code": "90b17137a2e9ce4abeedb56523b77740d346165d",
    "waktu_real_publish": "2024-04-14T09:46:00"
  },
  {
    "judul": "Kemenlu Sebut tidak Ada WNI Terdampak Serangan Iran ke Israel",
    "kategori": "Internasional",
    "waktu_publish": "1 jam yang lalu\n14 April 2024, 09:40",
    "waktu_scraping": "09:41:53\nSunday, 14 April 2024",
    "hash_code": "cbb0136a3a61d4bdd66218b8ba23fcad14c5f2dc",
    "waktu_real_publish": "2024-04-14T09:40:00"
  },
  {
    "judul": "Viral Keluhan Pungli di Masjid Al Jabbar, Pemprov Jabar Langsung Tertibkan",
    "kategori": "Rejabar",
    "waktu_publish": "1 jam yang lalu\n14 April 2024, 09:39",
    "waktu_scraping": "09:41:53\nSunday, 14 April 2024",
    "hash_code": "0ddef667bafb011864c942c22243699a4747779e",
    "waktu_real_publish": "2024-04-14T09:39:00"
  },
  {
    "judul": "Jumlah Gas Berbahaya di Atmosfer Terus Meningkat Selama Beberapa Dekade",
    "kategori": "Esgnow",
    "waktu_publish": "1 jam yang lalu\n14 April 2024, 09:29",
    "waktu_scraping": "09:31:53\nSunday, 14 April 2024",
    "hash_code": "47d65737e134423d90b896d3e4a8d6273e704311",
    "waktu_real_publish": "2024-04-14T09:29:00"
  },
  {
    "judul": "Satpol PP Badung Lakukan Operasi Yustisi di Terminal Mengwi",
    "kategori": "Visual",
    "waktu_publish": "1 jam yang lalu\n14 April 2024, 09:26",
    "waktu_scraping": "09:26:53\nSunday, 14 April 2024",
    "hash_code": "0c37e76710c3add3b5939f2e386339346bd0e116",
    "waktu_real_publish": "2024-04-14T09:26:00"
  },
  {
    "judul": "2 Gol Fernandes Antarkan MU Bawa Pulang Satu Poin dari Kandang Bournemouth",
    "kategori": "Sport",
    "waktu_publish": "1 jam yang lalu\n14 April 2024, 09:24",
    "waktu_scraping": "09:26:53\nSunday, 14 April 2024",
    "hash_code": "42f25b9a8aca7b44a1bf70f884a4956610209863",
    "waktu_real_publish": "2024-04-14T09:24:00"
  },
  {
    "judul": "Paman Sultan Agung Membunuh Dua Prajurit Tuban, Jadi Bukti akan Memberontak ke Pajang?",
    "kategori": "Network",
    "waktu_publish": "1 jam yang lalu\n14 April 2024, 09:07",
    "waktu_scraping": "09:16:53\nSunday, 14 April 2024",
    "hash_code": "20874a2395e9dcd08fa803e15c1f8b1f2a2d8412",
    "waktu_real_publish": "2024-04-14T09:07:00"
  },
  {
    "judul": "Puasa Sunnah Syawal 6 Hari, Apakah Harus Dilakukan Secara Berurutan atau Terpisah?",
    "kategori": "Islam Digest",
    "waktu_publish": "2 jam yang lalu\n14 April 2024, 08:36",
    "waktu_scraping": "08:36:53\nSunday, 14 April 2024",
    "hash_code": "228950cfdd385e7f1a661e03ddaebf4f6068f1d3",
    "waktu_real_publish": "2024-04-14T08:36:00"
  },
  {
    "judul": "Doa Pelunas Utang dan Mengapa Rasulullah SAW Selalu Mengulang-ulanginya?",
    "kategori": "Iqra",
    "waktu_publish": "2 jam yang lalu\n14 April 2024, 08:23",
    "waktu_scraping": "08:26:53\nSunday, 14 April 2024",
    "hash_code": "73ff0a2702647ee1bde48ecb6d26a9d1ce2023c7",
    "waktu_real_publish": "2024-04-14T08:23:00"
  },
  {
    "judul": "Tepi Barat Diguncang Serangan Brutal Pemukim Yahudi",
    "kategori": "Internasional",
    "waktu_publish": "2 jam yang lalu\n14 April 2024, 08:18",
    "waktu_scraping": "08:21:53\nSunday, 14 April 2024",
    "hash_code": "95927ab94c5131d3301c5f7be22a6970941dade0",
    "waktu_real_publish": "2024-04-14T08:18:00"
  },
  {
    "judul": "Iran Serang Israel, Kepanikan Warga Meluas Teriak Sembari Lari  dan Isyarat Alquran",
    "kategori": "Khazanah",
    "waktu_publish": "2 jam yang lalu\n14 April 2024, 08:05",
    "waktu_scraping": "08:06:22\nSunday, 14 April 2024",
    "hash_code": "1f59689d3286e8774769ab1fa803429b543bfd49",
    "waktu_real_publish": "2024-04-14T08:05:00"
  },
  {
    "judul": "Catat, Ini Cara Menghitung Zakat Mal",
    "kategori": "Sharia",
    "waktu_publish": "2 jam yang lalu\n14 April 2024, 08:05",
    "waktu_scraping": "08:06:22\nSunday, 14 April 2024",
    "hash_code": "73fb30af2c190f63a728b841eaac8ffb43d6ce14",
    "waktu_real_publish": "2024-04-14T08:05:00"
  },
  {
    "judul": "Iran Serang Israel, Kepanikan Warga Meluas Teriak Sembari Lari dan Isyarat Alquran",
    "kategori": "Khazanah",
    "waktu_publish": "2 jam yang lalu\n14 April 2024, 08:05",
    "waktu_scraping": "10:21:53\nSunday, 14 April 2024",
    "hash_code": "0f3b2211b39b840ae2422752ad5e21eb985fe5d4",
    "waktu_real_publish": "2024-04-14T08:05:00"
  },
  {
    "judul": "Rudal Iran Lintasi Al-Aqsa, Capai Target Militer di Israel",
    "kategori": "Internasional",
    "waktu_publish": "3 jam yang lalu\n14 April 2024, 07:11",
    "waktu_scraping": "08:06:22\nSunday, 14 April 2024",
    "hash_code": "4b766e1870d44783ce259632bc808fa05eb01ace",
    "waktu_real_publish": "2024-04-14T07:11:00"
  },
  {
    "judul": "Netanyahu dan Pejabat Israel Ngumpet dari Serangan Iran, Alquran Ungkap Yahudi Penakut",
    "kategori": "Iqra",
    "waktu_publish": "3 jam yang lalu\n14 April 2024, 07:08",
    "waktu_scraping": "08:06:22\nSunday, 14 April 2024",
    "hash_code": "0dc629d678ad0b332c3b848b45ab01442fcc4d3d",
    "waktu_real_publish": "2024-04-14T07:08:00"
  },
  {
    "judul": "Iran Tepati Janjinya Serang Israel, Orang Dekat Pemimpin Tertinggi Iran: Zionis Panik",
    "kategori": "Khazanah",
    "waktu_publish": "4 jam yang lalu\n14 April 2024, 06:48",
    "waktu_scraping": "08:06:22\nSunday, 14 April 2024",
    "hash_code": "deda330613a76315b1792fb1809ae0a7b94eaa6a",
    "waktu_real_publish": "2024-04-14T06:48:00"
  },
  {
    "judul": "UIN Yogyakarta Buka Tiga Jenis Seleksi Jalur Mandiri, Cek Ketentuan dan Jadwalnya",
    "kategori": "Network",
    "waktu_publish": "4 jam yang lalu\n14 April 2024, 06:41",
    "waktu_scraping": "08:06:22\nSunday, 14 April 2024",
    "hash_code": "9334f552186d5575695a1edaeefe638ea7690af4",
    "waktu_real_publish": "2024-04-14T06:41:00"
  },
  {
    "judul": "AS-Inggris dan Yordania Cegat Drone dan Rudal Iran menuju Israel",
    "kategori": "Internasional",
    "waktu_publish": "4 jam yang lalu\n14 April 2024, 06:41",
    "waktu_scraping": "08:06:22\nSunday, 14 April 2024",
    "hash_code": "c1944d49d7e5a0ecfe41db69d73ceee277bc11fc",
    "waktu_real_publish": "2024-04-14T06:41:00"
  },
  {
    "judul": "Lebaran Membawa Berkah Bagi Pedagang Pasar Malam Ikan Hias di Jakarta",
    "kategori": "News",
    "waktu_publish": "4 jam yang lalu\n14 April 2024, 06:34",
    "waktu_scraping": "08:06:22\nSunday, 14 April 2024",
    "hash_code": "e76aec732eb1467bfb20c4561f4e362ef7fd2bc1",
    "waktu_real_publish": "2024-04-14T06:34:00"
  },
  {
    "judul": "Pelni Bersiap Layani Puncak Arus Balik dari Pelabuhan Belawan",
    "kategori": "Ekonomi",
    "waktu_publish": "4 jam yang lalu\n14 April 2024, 06:30",
    "waktu_scraping": "08:06:22\nSunday, 14 April 2024",
    "hash_code": "df1c6e337c9b88f1793098d4e0e646eb7fd8efaf",
    "waktu_real_publish": "2024-04-14T06:30:00"
  },
  {
    "judul": "Respons Isu Normalisasi Indonesia-Israel, 3 Ormas Islam Sampaikan 8 Sikap Terbuka",
    "kategori": "Khazanah",
    "waktu_publish": "4 jam yang lalu\n14 April 2024, 06:28",
    "waktu_scraping": "08:06:22\nSunday, 14 April 2024",
    "hash_code": "760c47b0761f92911abcf42d3d89cfb3517e6d61",
    "waktu_real_publish": "2024-04-14T06:28:00"
  },
  {
    "judul": "Warga Rela Tunggu One Way untuk Libur Lebaran di Puncak Bogor",
    "kategori": "News",
    "waktu_publish": "4 jam yang lalu\n14 April 2024, 06:28",
    "waktu_scraping": "08:06:22\nSunday, 14 April 2024",
    "hash_code": "ffb32c0aa6d345bb4d40f9573a034e182d7ef2e6",
    "waktu_real_publish": "2024-04-14T06:28:00"
  },
  {
    "judul": "WFH untuk ASN dalam Mengatasi Kepadatan Arus Balik Lebaran 2024",
    "kategori": "Network",
    "waktu_publish": "4 jam yang lalu\n14 April 2024, 06:25",
    "waktu_scraping": "08:06:22\nSunday, 14 April 2024",
    "hash_code": "ba2186ed4ffef384a4de821f73173125d7a9a8e5",
    "waktu_real_publish": "2024-04-14T06:25:00"
  },
  {
    "judul": "Diserang Iran, Sirene dan Ledakan Terdengar di Seantero Israel",
    "kategori": "Internasional",
    "waktu_publish": "4 jam yang lalu\n14 April 2024, 06:20",
    "waktu_scraping": "08:06:22\nSunday, 14 April 2024",
    "hash_code": "5e8410157d6a26fecbb8ebdb788028b718fa6a4f",
    "waktu_real_publish": "2024-04-14T06:20:00"
  },
  {
    "judul": "Wisatawan Domestik ke Bali Keluarkan Uang Jutaan untuk Beli Oleh-Oleh",
    "kategori": "Ekonomi",
    "waktu_publish": "4 jam yang lalu\n14 April 2024, 06:18",
    "waktu_scraping": "08:06:22\nSunday, 14 April 2024",
    "hash_code": "9509774bbcb709fbf963512db7a4241bcdc770ac",
    "waktu_real_publish": "2024-04-14T06:18:00"
  },
  {
    "judul": "Bukan Adam, Inilah Makhluk Pertama yang Diciptakan Allah SWT",
    "kategori": "Network",
    "waktu_publish": "4 jam yang lalu\n14 April 2024, 06:16",
    "waktu_scraping": "08:06:22\nSunday, 14 April 2024",
    "hash_code": "23a389ef5d33323965831e2daee1da61900b80aa",
    "waktu_real_publish": "2024-04-14T06:16:00"
  },
  {
    "judul": "KAI Catat 3,1 Juta Tiket Terjual pada Masa Angkutan Lebaran 2024",
    "kategori": "Ekonomi",
    "waktu_publish": "4 jam yang lalu\n14 April 2024, 06:13",
    "waktu_scraping": "08:06:22\nSunday, 14 April 2024",
    "hash_code": "536f4ed336f9663acda8c2ef7c827c41841bc579",
    "waktu_real_publish": "2024-04-14T06:13:00"
  },
  {
    "judul": "Pengusaha Produk Spa di Bali Butuh SDM Bantu Wajib Sertifikasi Halal",
    "kategori": "Sharia",
    "waktu_publish": "4 jam yang lalu\n14 April 2024, 06:09",
    "waktu_scraping": "08:06:22\nSunday, 14 April 2024",
    "hash_code": "d9473d6a2a3459e293913dc734775a0bacac9843",
    "waktu_real_publish": "2024-04-14T06:09:00"
  },
  {
    "judul": "Serangan Iran ke Israel Dimulai, Netanyahu Ngumpet",
    "kategori": "News",
    "waktu_publish": "4 jam yang lalu\n14 April 2024, 06:09",
    "waktu_scraping": "08:06:22\nSunday, 14 April 2024",
    "hash_code": "1f20e9e4aecccb7f2273c46ef7ce3ccd07586ad2",
    "waktu_real_publish": "2024-04-14T06:09:00"
  },
  {
    "judul": "PUPR: Pansela Kurangi Beban Tol Trans Jawa Sekaligus Jadi Jalur Wisata",
    "kategori": "Ekonomi",
    "waktu_publish": "5 jam yang lalu\n14 April 2024, 05:40",
    "waktu_scraping": "08:06:22\nSunday, 14 April 2024",
    "hash_code": "587402c34657984650ee8b9959c78d71e86e9b34",
    "waktu_real_publish": "2024-04-14T05:40:00"
  },
  {
    "judul": "KSOP: Pelabuhan Panjang Layani Arus Balik Hingga 18 April",
    "kategori": "Ekonomi",
    "waktu_publish": "5 jam yang lalu\n14 April 2024, 05:30",
    "waktu_scraping": "08:06:22\nSunday, 14 April 2024",
    "hash_code": "6ce111df1ad73bf91f436e9cc700c7623deb46ad",
    "waktu_real_publish": "2024-04-14T05:30:00"
  },
  {
    "judul": "Daftar 10 KA Jarak Jauh dan Relasi Favorit Penumpang di Lebaran 2024",
    "kategori": "Network",
    "waktu_publish": "6 jam yang lalu\n14 April 2024, 04:40",
    "waktu_scraping": "08:06:22\nSunday, 14 April 2024",
    "hash_code": "9bf0c75b246c94654c5cf4a01420f520d62150e9",
    "waktu_real_publish": "2024-04-14T04:40:00"
  },
  {
    "judul": "Koleksi Kuno Kesultanan Palembang Darussalam, Ada Jubah SMB II",
    "kategori": "Network",
    "waktu_publish": "6 jam yang lalu\n14 April 2024, 04:40",
    "waktu_scraping": "08:06:22\nSunday, 14 April 2024",
    "hash_code": "4c77f37ae1b62c429a7ea219cb5b5ae700c4296d",
    "waktu_real_publish": "2024-04-14T04:40:00"
  },
  {
    "judul": "3,1 Juta Tiket KA Jarak Jauh pada Masa Angkutan Lebaran Telah Terjual",
    "kategori": "Network",
    "waktu_publish": "6 jam yang lalu\n14 April 2024, 04:40",
    "waktu_scraping": "08:06:22\nSunday, 14 April 2024",
    "hash_code": "662d986d894f9f82c926c24973ac1987edd4617b",
    "waktu_real_publish": "2024-04-14T04:40:00"
  },
  {
    "judul": "Wajib Tahu, Dahsyat Khasiat Manfaat Daun Seledri Bagi Kesehatan Tubuh",
    "kategori": "Network",
    "waktu_publish": "6 jam yang lalu\n14 April 2024, 04:40",
    "waktu_scraping": "08:06:22\nSunday, 14 April 2024",
    "hash_code": "3e30f6a0db8fcf2d8d284183184eaebd61fa41f3",
    "waktu_real_publish": "2024-04-14T04:40:00"
  },
  {
    "judul": "Tiga Orang yang Dilaknat Allah",
    "kategori": "Network",
    "waktu_publish": "6 jam yang lalu\n14 April 2024, 04:31",
    "waktu_scraping": "08:06:22\nSunday, 14 April 2024",
    "hash_code": "d78da89b5e3672b8e9164a4bc47dcc034809c7f6",
    "waktu_real_publish": "2024-04-14T04:31:00"
  },
  {
    "judul": "KAI Bandung Sebut Arus Balik Lebaran 2024 Sudah Terasa",
    "kategori": "News",
    "waktu_publish": "6 jam yang lalu\n14 April 2024, 04:28",
    "waktu_scraping": "08:06:22\nSunday, 14 April 2024",
    "hash_code": "a4763abb061348d79b855b60843a55939eb3e181",
    "waktu_real_publish": "2024-04-14T04:28:00"
  },
  {
    "judul": "Kunjungan Wisata Religi di Kalimantan Selatan Naik Usai Lebaran",
    "kategori": "Khazanah",
    "waktu_publish": "6 jam yang lalu\n14 April 2024, 04:25",
    "waktu_scraping": "08:06:22\nSunday, 14 April 2024",
    "hash_code": "7dfed5f1314edabb15a5f8f632fde3e025ee7bb7",
    "waktu_real_publish": "2024-04-14T04:25:00"
  },
  {
    "judul": "Pakar: Indonesia Perlu Maksimalkan Produksi Pangan yang Sesuai",
    "kategori": "Ekonomi",
    "waktu_publish": "7 jam yang lalu\n14 April 2024, 03:40",
    "waktu_scraping": "08:06:22\nSunday, 14 April 2024",
    "hash_code": "72a6bee5b26c3e0f5aa193fb8e07e3449130d1d2",
    "waktu_real_publish": "2024-04-14T03:40:00"
  },
  {
    "judul": "BREAKING NEWS: Iran Lancarkan Serangan, Kirim Drone Kamikaze ke Israel",
    "kategori": "Internasional",
    "waktu_publish": "7 jam yang lalu\n14 April 2024, 03:22",
    "waktu_scraping": "08:06:22\nSunday, 14 April 2024",
    "hash_code": "8111c3e9c94366d3c30a93a3bfebe32a6b36a233",
    "waktu_real_publish": "2024-04-14T03:22:00"
  },
  {
    "judul": "Gobel: Penciptaan Lapangan Kerja Solusi Terbaik Berantas Kemiskinan",
    "kategori": "Ekonomi",
    "waktu_publish": "7 jam yang lalu\n14 April 2024, 03:20",
    "waktu_scraping": "08:06:22\nSunday, 14 April 2024",
    "hash_code": "9522997de7113e30556dba58f802f3995faafca7",
    "waktu_real_publish": "2024-04-14T03:20:00"
  },
  {
    "judul": "BRGM Dorong Pembentukan Peraturan Hukum Desa untuk Lindungi Gambut",
    "kategori": "Esgnow",
    "waktu_publish": "7 jam yang lalu\n14 April 2024, 03:10",
    "waktu_scraping": "08:06:22\nSunday, 14 April 2024",
    "hash_code": "f0cbf0e7bbe0c5ae95cc0d90ec79ad3585c6b51a",
    "waktu_real_publish": "2024-04-14T03:10:00"
  },
  {
    "judul": "Israel Setop Aktivitas Sekolah, Netanyahu 'Mengungsi' ke Bunker, Serangan Iran Kian Dekat",
    "kategori": "Internasional",
    "waktu_publish": "7 jam yang lalu\n14 April 2024, 02:55",
    "waktu_scraping": "08:06:22\nSunday, 14 April 2024",
    "hash_code": "81311f0ce8e3becb632f79b712cecad56ee4a04d",
    "waktu_real_publish": "2024-04-14T02:55:00"
  },
  {
    "judul": "Perempuan Gayo Aceh Dibina Kembangkan Produk Serat Nanas",
    "kategori": "News",
    "waktu_publish": "8 jam yang lalu\n14 April 2024, 02:50",
    "waktu_scraping": "08:06:22\nSunday, 14 April 2024",
    "hash_code": "390626616883ba4b8165025206777a15245f682d",
    "waktu_real_publish": "2024-04-14T02:50:00"
  },
  {
    "judul": "BKKBN Tekankan Pentingnya Peran Ibu Bagi Keluarga",
    "kategori": "Ameera",
    "waktu_publish": "8 jam yang lalu\n14 April 2024, 02:40",
    "waktu_scraping": "08:06:22\nSunday, 14 April 2024",
    "hash_code": "6ded074236e697c8410c04730d8312b8672a7e37",
    "waktu_real_publish": "2024-04-14T02:40:00"
  },
  {
    "judul": "Jadwal Olahraga Ahad: Jonatan Christie Berlaga di Final Kejuaraan Bulu Tangkis Asia",
    "kategori": "Sport",
    "waktu_publish": "8 jam yang lalu\n14 April 2024, 02:36",
    "waktu_scraping": "08:06:22\nSunday, 14 April 2024",
    "hash_code": "0366c130b5a166dd745ba4544380663ad2694a94",
    "waktu_real_publish": "2024-04-14T02:36:00"
  },
  {
    "judul": "Jasa Raharja Gandeng Guru Bangun Kesadaran Siswa Jaga Keselamatan Berlalu Lintas",
    "kategori": "Ekonomi",
    "waktu_publish": "8 jam yang lalu\n14 April 2024, 02:30",
    "waktu_scraping": "08:06:22\nSunday, 14 April 2024",
    "hash_code": "7fe96d7be4c93075080d349e0a207d8fdfe7470b",
    "waktu_real_publish": "2024-04-14T02:30:00"
  },
  {
    "judul": "Menperin: Potensi Besar Industri Halal Harus Kita Ambil",
    "kategori": "Sharia",
    "waktu_publish": "8 jam yang lalu\n14 April 2024, 02:20",
    "waktu_scraping": "08:06:22\nSunday, 14 April 2024",
    "hash_code": "cd3c1a9ce4997c8900c57a854f8ebd8245bedc3d",
    "waktu_real_publish": "2024-04-14T02:20:00"
  },
  {
    "judul": "BKKBN Ingatkan Pentingnya Keluarga Turunkan Nilai Luhur kepada Anak",
    "kategori": "Ameera",
    "waktu_publish": "8 jam yang lalu\n14 April 2024, 02:10",
    "waktu_scraping": "08:06:22\nSunday, 14 April 2024",
    "hash_code": "f2b5bc1a18141fc4a92577b8256221703abf22a5",
    "waktu_real_publish": "2024-04-14T02:10:00"
  },
  {
    "judul": "Ini Antisipasi Polri Cegah Kecelakaan Saat Pemberlakuan Contraflow Arus Balik",
    "kategori": "News",
    "waktu_publish": "8 jam yang lalu\n14 April 2024, 02:01",
    "waktu_scraping": "08:06:22\nSunday, 14 April 2024",
    "hash_code": "611604730e07d41ca02b21ffce2510a7de251216",
    "waktu_real_publish": "2024-04-14T02:01:00"
  },
  {
    "judul": "Bappebti: Perdagangan Kripto jadi Strategi Percepatan Ekonomi Digital",
    "kategori": "Ekonomi",
    "waktu_publish": "9 jam yang lalu\n14 April 2024, 01:50",
    "waktu_scraping": "08:06:22\nSunday, 14 April 2024",
    "hash_code": "ba6e13f09ba9ea19ffdaa39efe1348b43cdd456c",
    "waktu_real_publish": "2024-04-14T01:50:00"
  },
  {
    "judul": "Fraksi PKS Apresiasi Menlu Tegas Bantah Isu Normalisasi Hubungan RI dengan Israel",
    "kategori": "News",
    "waktu_publish": "9 jam yang lalu\n14 April 2024, 01:48",
    "waktu_scraping": "08:06:22\nSunday, 14 April 2024",
    "hash_code": "d551b5e8a6bcb089a23179cfc7e6d473eabb6c3a",
    "waktu_real_publish": "2024-04-14T01:48:00"
  },
  {
    "judul": "Bristol Rovers Kalahkan Cheltenham 3-1, Elkan Baggott Cetak Gol",
    "kategori": "Sport",
    "waktu_publish": "9 jam yang lalu\n14 April 2024, 01:43",
    "waktu_scraping": "08:06:22\nSunday, 14 April 2024",
    "hash_code": "d006834e89b29658a77ba2966dfb1d1ff992241a",
    "waktu_real_publish": "2024-04-14T01:43:00"
  },
  {
    "judul": "Indonesia Kaya Potensi Obat Herbal untuk Hewan",
    "kategori": "Ekonomi",
    "waktu_publish": "9 jam yang lalu\n14 April 2024, 01:40",
    "waktu_scraping": "08:06:22\nSunday, 14 April 2024",
    "hash_code": "e16f1909e7efdd512e3acdfdb9c4465443eeec53",
    "waktu_real_publish": "2024-04-14T01:40:00"
  },
  {
    "judul": "Polres Bogor Tindak Bengkel Mobil di Kawasan Puncak Lakukan Getok Harga ke Konsumen",
    "kategori": "News",
    "waktu_publish": "9 jam yang lalu\n14 April 2024, 01:30",
    "waktu_scraping": "08:06:22\nSunday, 14 April 2024",
    "hash_code": "86412aa481bb5995ddb869fe5f29365d71b7bb4a",
    "waktu_real_publish": "2024-04-14T01:30:00"
  },
  {
    "judul": "Bappenas: Industrialisasi Percepat Pertumbuhan Ekonomi Menuju Negara Maju",
    "kategori": "Ekonomi",
    "waktu_publish": "9 jam yang lalu\n14 April 2024, 01:30",
    "waktu_scraping": "08:06:22\nSunday, 14 April 2024",
    "hash_code": "4330b61a3ee7e4788e05e154807bd46e13a32d3e",
    "waktu_real_publish": "2024-04-14T01:30:00"
  },
  {
    "judul": "Psikolog: Banyak Quality Time dengan Anak Berdampak Hingga Dewasa",
    "kategori": "Ameera",
    "waktu_publish": "9 jam yang lalu\n14 April 2024, 01:20",
    "waktu_scraping": "08:06:22\nSunday, 14 April 2024",
    "hash_code": "0e3bfe1450caa6add72375a0b3cb27ca43419531",
    "waktu_real_publish": "2024-04-14T01:20:00"
  },
  {
    "judul": "BRIN: Pemanfaatan Obat Herbal untuk Hewan Kian Masif",
    "kategori": "Ekonomi",
    "waktu_publish": "9 jam yang lalu\n14 April 2024, 01:10",
    "waktu_scraping": "08:06:22\nSunday, 14 April 2024",
    "hash_code": "5a232f1fa754393b540168d1177aa86198bd28b4",
    "waktu_real_publish": "2024-04-14T01:10:00"
  },
  {
    "judul": "Polres Bogor Berlakukan One Way di Kawasan Puncak Selama 10 Jam",
    "kategori": "News",
    "waktu_publish": "9 jam yang lalu\n14 April 2024, 01:09",
    "waktu_scraping": "08:06:22\nSunday, 14 April 2024",
    "hash_code": "4398c2a9d7ab6044a8066a243513b844ef2c3817",
    "waktu_real_publish": "2024-04-14T01:09:00"
  },
  {
    "judul": "Vinales, Acosta, dan Marquez Start dari Baris Depan di GP Amerika",
    "kategori": "Sport",
    "waktu_publish": "9 jam yang lalu\n14 April 2024, 01:06",
    "waktu_scraping": "08:06:22\nSunday, 14 April 2024",
    "hash_code": "19275142d143bd914bc9fae67b6d12b526c8857e",
    "waktu_real_publish": "2024-04-14T01:06:00"
  },
  {
    "judul": "Gasak Luton Town 5-1, Manchester City Sementara di Puncak Klasemen Liga Primer Inggris",
    "kategori": "Sport",
    "waktu_publish": "9 jam yang lalu\n14 April 2024, 01:01",
    "waktu_scraping": "08:06:22\nSunday, 14 April 2024",
    "hash_code": "c602dcba0d2040c29eed27642ef3a5fdb7f90ff0",
    "waktu_real_publish": "2024-04-14T01:01:00"
  }
]